{
  "1": "ST",
  "2": "LB",
  "3": "最大",
  "4": "回復",
  "5": "{0}が最大のため、回復できません。",
  "6": "アイテム使用期限終了",
  "7": "使用期限が終了しているアイテムが含まれていたため、\n{0}の回復を行えませんでした。",
  "8": "全回復まであと",
  "9": "全回復済み",
  "10": "回復量選択",
  "11": "最大ST (100) を超える場合は加算されます。",
  "12": "最大LB (10) を超える場合は加算されます。",
  "13": "回復アイテム選択確認",
  "14": "使用できる{0}回復アイテムはありません。",
  "15": "以下のアイテムを使って\n{0}を{1}回復します。よろしいですか？",
  "16": "回復完了",
  "17": "アイテムを使用して、{0}を{1}回復しました。",
  "18": "プリズムジュエルを{0}個使用して、{1}を{2}回復しました。",
  "19": "プリズムジュエルを{0}個使用するごとに、{1}を{2}回復します。",
  "20": "回復量確認",
  "21": "プリズムジュエルを{0}個使用して、{1}を{2}回復しますか？",
  "22": "リセット",
  "23": "必要",
  "24": "所持",
  "25": "<sprite=3>無償プリズムジュエルから先に使用されます。",
  "26": "回復量",
  "27": "使用数",
  "28": "回復アイテム選択",
  "29": "不足",
  "30": "プロデュースをプレイするために必要なSTが不足しています。"
}